betterpy_i_make_modules/__init__.py
betterpy_i_make_modules/betterpy.py
betterpy_i_make_modules-0.0.2.dist-info/LICENSE.txt
betterpy_i_make_modules-0.0.2.dist-info/METADATA
betterpy_i_make_modules-0.0.2.dist-info/WHEEL
betterpy_i_make_modules-0.0.2.dist-info/top_level.txt
betterpy_i_make_modules-0.0.2.dist-info/RECORD
