Metadata-Version: 2.1
Name: betterpy-i-make-modules
Version: 0.0.2
Summary: A package that minimizes your python code
Author-email: Noor Hossam <emailforemails64@gmail.com>
Project-URL: Homepage, https://github.com/
Project-URL: Bug Tracker, https://github.com/
Classifier: Programming Language :: Python :: 3
Classifier: License :: OSI Approved :: MIT License
Classifier: Operating System :: OS Independent
Requires-Python: >=0.1
License-File: LICENSE.txt
